django_unsigned_fields/__init__.py
django_unsigned_fields/compat.py
django_unsigned_fields/fields.py
django_unsigned_fields/models.py
django_unsigned_fields/six.py
django_unsigned_fields-1.3.0.dist-info/DESCRIPTION.rst
django_unsigned_fields-1.3.0.dist-info/METADATA
django_unsigned_fields-1.3.0.dist-info/metadata.json
django_unsigned_fields-1.3.0.dist-info/RECORD
django_unsigned_fields-1.3.0.dist-info/top_level.txt
django_unsigned_fields-1.3.0.dist-info/WHEEL
