Metadata-Version: 2.0
Name: django-unsigned-fields
Version: 1.3.0
Summary: Django fields for using unsigned integers for relationships
Home-page: https://github.com/simpleenergy/django-unsigned-fields
Author: Piper Merriam
Author-email: piper@simpleenergy.com
License: BSD
Keywords: django-unsigned-fields
Platform: UNKNOWN
Classifier: Development Status :: 2 - Pre-Alpha
Classifier: Framework :: Django
Classifier: Intended Audience :: Developers
Classifier: License :: OSI Approved :: BSD License
Classifier: Natural Language :: English
Classifier: Programming Language :: Python :: 2
Classifier: Programming Language :: Python :: 2.6
Classifier: Programming Language :: Python :: 2.7
Classifier: Programming Language :: Python :: 3
Classifier: Programming Language :: Python :: 3.3
Requires-Dist: django (>=1.4)
